Workbook

Sheet Dados
A1: Ano-Calendário | B1: Gênero | C1: Faixa SM Mensal | D1: Quantidade de Declarantes | E1: Rendimentos Tributáveis | F1: Rendimentos sujeitos a Tributação Exclusiva | G1: Rendimentos Isentos | H1: Dedução Previdenciária Total | I1: Deduções Previdência Oficial | J1: Deduções Previdenciárias RRA | K1: Deduções Previdência Privada e FAPI | L1: Deduções com Dependentes | M1: Deduções com Instrução | N1: Deduções com despesas Médicas | O1: Dedução de Livro Caixa | P1: Deduções com Pensão Alimentícia Total | Q1: Deduções com Pensão Alimentícia Judicial | R1: Deduções com Pensão Alimentícia Escritural | S1: Deduções com Pensão Alimentícia RRA | T1: Desconto Padrão | U1: Base de Cálculo (RTL) | V1: Imposto Devido | W1: Dedução de Incentivo | X1: Imposto Devido 1 | Y1: Imposto Devido RRA | Z1: Imposto Devido Total | AA1: Imposto Pago | AB1: Imposto a Pagar | AC1: Imposto a Restituir | AD1: Dívidas e Ônus | AE1: Doações e Heranças Recebidas | AF1: Bens e Direitos | AG1: Previdência Complementar (VGBL) | AH1: Valores Pagos com Previdência Complementar (PGBL) | AI1: Valores Pagos com Previdência Complementar de Natureza Pública | AJ1: Valores Pagos com FAPI | AK1: Despesas com Instrução | AL1: Despesas Médicas | AM1: Pensão Alimentícia Judicial | AN1: Despesas com Pensão Alimentícia Escritural | AO1: Despesas com Profissionais Liberais | AP1: Despesas com Arrendamento Rural | AQ1: Outras Despesas | AR1: Doações Efetuadas
A2: 2020 | B2: Masculino | C2: Até 1/2 | D2: 1938404 | E2: 6028.8902 | F2: 21232.75 | G2: 136168.76 | H2: 674.37699 | I2: 638.43801 | J2: 1.3385559 | K2: 34.60043 | L2: 508.05671 | M2: 164.2155 | N2: 1969.7394 | O2: 203.19778 | P2: 597.20319 | Q2: 503.68287 | R2: 93.175601 | S2: 0.34472372 | T2: 232.91939 | U2: 1679.1813 | V2: 0.37787763 | W2: 0 | X2: 0.37787763 | Y2: 94.438722 | Z2: 94.480637 | AA2: 446.09271 | AB2: 7.2056446 | AC2: 358.05491 | AD2: 84122.932 | AE2: 10809.601 | AF2: 1145149.1 | AG2: 6633.8065 | AH2: 289.54648 | AI2: 3.0982198 | AJ2: 94.363618 | AK2: 1421.3546 | AL2: 5655.3933 | AM2: 1394.4638 | AN2: 245.14585 | AO2: 876.38982 | AP2: 82.345182 | AQ2: 2157.6331 | AR2: 6448.6204
A3: 2020 | B3: Masculino | C3: De 1/2 a 1 | D3: 1194585 | E3: 16224.937 | F3: 6940.1964 | G3: 66743.173 | H3: 427.23076 | I3: 407.21008 | J3: 0.43952543 | K3: 19.58115 | L3: 440.13698 | M3: 115.50035 | N3: 1016.6703 | O3: 91.318402 | P3: 226.10305 | Q3: 197.36928 | R3: 28.284649 | S3: 0.4491214 | T3: 2053.055 | U3: 11854.922 | V3: 0.36433747 | W3: 0 | X3: 0.36433747 | Y3: 21.629415 | Z3: 21.946183 | AA3: 158.31987 | AB3: 1.4307317 | AC3: 137.68981 | AD3: 35356.143 | AE3: 3142.2507 | AF3: 405535.09 | AG3: 2605.2066 | AH3: 66.996681 | AI3: 1.2896696 | AJ3: 18.424274 | AK3: 523.86093 | AL3: 1561.4217 | AM3: 281.28179 | AN3: 43.148206 | AO3: 238.84813 | AP3: 19.100004 | AQ3: 700.15891 | AR3: 1647.8399
A4: 2020 | B4: Masculino | C4: De 1 a 2 | D4: 4345329 | E4: 117488.44 | F4: 17993.684 | G4: 106779.15 | H4: 3427.5925 | I4: 3276.5032 | J4: 2.9205423 | K4: 148.16874 | L4: 3434.5859 | M4: 1359.1252 | N4: 5054.364 | O4: 605.36347 | P4: 1577.8889 | Q4: 1419.9976 | R4: 155.43457 | S4: 2.4567671 | T4: 14318.396 | U4: 87711.188 | V4: 84.984149 | W4: 0.00147271 | X4: 84.982676 | Y4: 45.336608 | Z4: 129.93403 | AA4: 1314.7173 | AB4: 20.386877 | AC4: 1208.7116 | AD4: 65852.939 | AE4: 6776.7297 | AF4: 976540.2 | AG4: 6070.0437 | AH4: 227.93414 | AI4: 4.7330037 | AJ4: 83.007879 | AK4: 2869.5418 | AL4: 6536.228 | AM4: 1609.3351 | AN4: 184.313 | AO4: 648.9355 | AP4: 35.596685 | AQ4: 1305.3696 | AR4: 2922.7165
A5: 2020 | B5: Masculino | C5: De 2 a 3 | D5: 3831780 | E5: 157236.28 | F5: 21143.659 | G5: 67960.628 | H5: 5643.2947 | I5: 5345.4965 | J5: 3.5004749 | K5: 294.29766 | L5: 4260.7858 | M5: 2080.9688 | N5: 6249.303 | O5: 713.07388 | P5: 1906.7421 | Q5: 1717.4575 | R5: 187.59816 | S5: 1.6864167 | T5: 19094.186 | U5: 117287.96 | V5: 2346.0755 | W5: 0.21882066 | X5: 2345.8567 | Y5: 46.05825 | Z5: 2391.6583 | AA5: 4335.1626 | AB5: 370.97103 | AC5: 2329.8165 | AD5: 56741.612 | AE5: 3811.9995 | AF5: 704797.78 | AG5: 3787.817 | AH5: 306.73758 | AI5: 5.7570917 | AJ5: 144.28444 | AK5: 3986.508 | AL5: 7403.5664 | AM5: 1774.8479 | AN5: 195.11187 | AO5: 607.97244 | AP5: 33.720747 | AQ5: 1316.937 | AR5: 2165.0436
A6: 2020 | B6: Masculino | C6: De 3 a 5 | D6: 3129461 | E6: 200239.99 | F6: 28763.208 | G6: 91109.034 | H6: 8038.5069 | I6: 7376.1479 | J6: 4.8745383 | K6: 657.48443 | L6: 3769.2456 | M6: 2730.1335 | N6: 8282.4504 | O6: 1064.0368 | P6: 2690.429 | Q6: 2417.9965 | R6: 270.62808 | S6: 1.804453 | T6: 23505.599 | U6: 150159.63 | V6: 10372.014 | W6: 2.1100343 | X6: 10369.904 | Y6: 85.351126 | Z6: 10454.118 | AA6: 12587.346 | AB6: 1660.7971 | AC6: 3860.2593 | AD6: 78103.816 | AE6: 5284.8562 | AF6: 973120.82 | AG6: 6761.668 | AH6: 686.24947 | AI6: 14.367929 | AJ6: 281.26952 | AK6: 5934.8982 | AL6: 10324.456 | AM6: 2495.2338 | AN6: 279.98782 | AO6: 876.7974 | AP6: 63.096117 | AQ6: 1948.4569 | AR6: 3485.6349
A7: 2020 | B7: Masculino | C7: De 5 a 7 | D7: 1133953 | E7: 109774.66 | F7: 15865.399 | G7: 43864.163 | H7: 5315.9362 | I7: 4601.6575 | J7: 2.4380657 | K7: 711.84062 | L7: 1719.0595 | M7: 1487.3542 | N7: 5076.528 | O7: 658.72624 | P7: 1819.7595 | Q7: 1630.483 | R7: 188.46054 | S7: 0.81595256 | T7: 10147.716 | U7: 83549.587 | V7: 11150.087 | W7: 3.98164 | X7: 11146.106 | Y7: 45.493646 | Z7: 11190.613 | AA7: 11360.752 | AB7: 1614.51 | AC7: 1842.8896 | AD7: 42124.722 | AE7: 2773.6901 | AF7: 513134.56 | AG7: 3236.8326 | AH7: 682.48194 | AI7: 21.139401 | AJ7: 258.46861 | AK7: 3487.0496 | AL7: 6172.4541 | AM7: 1664.1419 | AN7: 194.37633 | AO7: 455.61076 | AP7: 40.812555 | AQ7: 1141.0441 | AR7: 2152.3751
A8: 2020 | B8: Masculino | C8: De 7 a 10 | D8: 895927 | E8: 117600.72 | F8: 18304.304 | G8: 41392.165 | H8: 7117.6588 | I8: 5888.6096 | J8: 3.4735579 | K8: 1225.5757 | L8: 1610.4905 | M8: 1357.9107 | N8: 5600.3899 | O8: 635.3276 | P8: 1807.9684 | Q8: 1603.0235 | R8: 204.06125 | S8: 0.8836353 | T8: 5922.9943 | U8: 93547.984 | V8: 16381.666 | W8: 9.4535928 | X8: 16372.212 | Y8: 58.682017 | Z8: 16430.822 | AA8: 15992.162 | AB8: 1901.8763 | AC8: 1533.3443 | AD8: 42122.367 | AE8: 3088.3061 | AF8: 513465.1 | AG8: 3605.6625 | AH8: 1083.6626 | AI8: 75.998951 | AJ8: 359.51106 | AK8: 3525.3121 | AL8: 6323.3383 | AM8: 1618.8329 | AN8: 206.42787 | AO8: 497.34949 | AP8: 27.038666 | AQ8: 1343.1 | AR8: 2806.0815
A9: 2020 | B9: Masculino | C9: De 10 a 15 | D9: 691586 | E9: 128920.31 | F9: 20501.19 | G9: 41435.868 | H9: 9441.0698 | I9: 7402.2784 | J9: 2.8942855 | K9: 2035.8971 | L9: 1407.6329 | M9: 1178.752 | N9: 6044.951 | O9: 737.47585 | P9: 1882.5588 | Q9: 1659.2791 | R9: 222.68421 | S9: 0.59545987 | T9: 2890.0901 | U9: 105337.79 | V9: 21755.945 | W9: 21.189555 | X9: 21734.755 | Y9: 73.36934 | Z9: 21807.712 | AA9: 21144.771 | AB9: 1997.7897 | AC9: 1420.2694 | AD9: 43417.492 | AE9: 3428.6727 | AF9: 594008.2 | AG9: 4902.5033 | AH9: 1709.5933 | AI9: 124.42848 | AJ9: 506.19405 | AK9: 3743.7515 | AL9: 6532.0899 | AM9: 1673.0643 | AN9: 224.48046 | AO9: 547.34187 | AP9: 29.774981 | AQ9: 1694.0377 | AR9: 2719.6251
A10: 2020 | B10: Masculino | C10: De 15 a 20 | D10: 308224 | E10: 79933.156 | F10: 14179.229 | G10: 26666.559 | H10: 6409.13 | I10: 4792.9131 | J10: 2.3039801 | K10: 1613.9129 | L10: 660.5854 | M10: 562.4392 | N10: 3456.4143 | O10: 554.71656 | P10: 1055.9763 | Q10: 928.76617 | R10: 126.51846 | S10: 0.69171156 | T10: 847.1832 | U10: 66386.707 | V10: 15042.455 | W10: 21.657668 | X10: 15020.797 | Y10: 53.605317 | Z10: 15074.152 | AA10: 14517.715 | AB10: 1224.9329 | AC10: 729.84055 | AD10: 25431.487 | AE10: 2458.0832 | AF10: 409652.44 | AG10: 3257.9541 | AH10: 1403.3385 | AI10: 80.715602 | AJ10: 336.92248 | AK10: 2205.0779 | AL10: 3681.5247 | AM10: 935.38358 | AN10: 127.54354 | AO10: 352.54615 | AP10: 17.010213 | AQ10: 1332.9795 | AR10: 2004.7502
A11: 2020 | B11: Masculino | C11: De 20 a 30 | D11: 253798 | E11: 91529.792 | F11: 17396.975 | G11: 32293.22 | H11: 7602.2657 | I11: 5634.3064 | J11: 2.826982 | K11: 1965.1323 | L11: 571.62523 | M11: 499.71665 | N11: 3678.6923 | O11: 859.14121 | P11: 1022.4568 | Q11: 895.70787 | R11: 126.30679 | S11: 0.44218657 | T11: 526.1868 | U11: 76769.707 | V11: 18465.572 | W11: 34.69181 | X11: 18430.88 | Y11: 78.478673 | Z11: 18509.348 | AA11: 17808.005 | AB11: 1419.0356 | AC11: 810.8064 | AD11: 35788.424 | AE11: 2728.3238 | AF11: 522849.51 | AG11: 4276.0598 | AH11: 1681.1975 | AI11: 171.73195 | AJ11: 355.73916 | AK11: 2456.9082 | AL11: 3911.7706 | AM11: 903.185 | AN11: 127.18728 | AO11: 371.15142 | AP11: 19.575084 | AQ11: 1426.6533 | AR11: 2829.7323
A12: 2020 | B12: Masculino | C12: De 30 a 40 | D12: 68596 | E12: 33188.293 | F12: 7571.303 | G12: 14708.785 | H12: 2328.7747 | I12: 1567.3595 | J12: 0.97485588 | K12: 760.44041 | L12: 160.90958 | M12: 147.54653 | N12: 1032.3067 | O12: 485.49353 | P12: 254.8684 | Q12: 220.44031 | R12: 34.404468 | S12: 0.02362481 | T12: 150.23617 | U12: 28628.158 | V12: 7157.7876 | W12: 17.048014 | X12: 7140.7395 | Y12: 32.205 | Z12: 7172.9445 | AA12: 6658.0199 | AB12: 645.25728 | AC12: 193.40276 | AD12: 13281.472 | AE12: 1223.8153 | AF12: 210481.09 | AG12: 1701.3871 | AH12: 665.77583 | AI12: 59.337565 | AJ12: 128.95534 | AK12: 869.64049 | AL12: 1118.141 | AM12: 223.68475 | AN12: 34.732703 | AO12: 131.92825 | AP12: 10.040748 | AQ12: 532.5292 | AR12: 1285.019
A13: 2020 | B13: Masculino | C13: De 40 a 60 | D13: 49029 | E13: 31950.203 | F13: 9563.5656 | G13: 21350.971 | H13: 1544.7062 | I13: 712.99608 | J13: 1.7972984 | K13: 829.91279 | L13: 117.4328 | M13: 108.48284 | N13: 716.96551 | O13: 752.744 | P13: 220.08379 | Q13: 187.391 | R13: 32.641418 | S13: 0.05137208 | T13: 149.5995 | U13: 28340.188 | V13: 7283.0786 | W13: 20.873241 | X13: 7262.2054 | Y13: 18.844039 | Z13: 7281.0489 | AA13: 6439.2856 | AB13: 873.88724 | AC13: 183.59131 | AD13: 20237.557 | AE13: 1608.517 | AF13: 295655.71 | AG13: 3888.0756 | AH13: 743.5564 | AI13: 4.2578805 | AJ13: 137.99888 | AK13: 803.04424 | AL13: 804.63966 | AM13: 188.44175 | AN13: 32.85094 | AO13: 152.20746 | AP13: 17.635447 | AQ13: 513.90341 | AR13: 3356.1145
... A176: 2016 | B176: Não declarado | C176: Todas | D176: 2831 | E176: 148.59067 | F176: 15.461379 | G176: 42.166639 | H176: 6.7154186 | I176: 5.787439 | J176: 0.0069444 | K176: 0.92103526 | L176: 3.9909233 | M176: 2.6118005 | N176: 6.0787323 | O176: 0.96915659 | P176: 1.7604832 | Q176: 1.5696345 | R176: 0.19084867 | S176: 0 | T176: 12.692819 | U176: 113.77134 | V176: 11.637488 | W176: 0.00097 | X176: 11.636518 | Y176: 0.00683592 | Z176: 11.618748 | AA176: 12.489894 | AB176: 1.3684141 | AC176: 2.3215774 | AD176: 25.94103 | AE176: 1.3324596 | AF176: 383.52385 | AG176: 3.5299071 | AH176: 0.98457281 | AI176: 0.00284129 | AJ176: 0.28741372 | AK176: 4.7241692 | AL176: 7.5264485 | AM176: 1.6295368 | AN176: 0.20525638 | AO176: 0.28625612 | AP176: 0.008 | AQ176: 0.8243797 | AR176: 2.8423768
A177: 2015 | B177: Masculino | C177: até 1/2 | D177: 1495807.3 | E177: 3219.17 | F177: 15740.32 | G177: 90208.665 | H177: 2179.9245 | L177: 1163.3906 | M177: 220.1541 | N177: 2547.1026 | O177: 145.39151 | P177: 1176.082 | T177: 97.381326 | U177: 689.75937 | V177: 0.018989527 | AA177: 245.58757 | AB177: 8.2443966 | AC177: 207.94185 | AD177: 93178.688 | AE177: 9259.2464 | AF177: 586396.06
A178: 2015 | B178: Masculino | C178: de 1/2 a 1 | D178: 795206.12 | E178: 8198.6076 | F178: 3264.7241 | G178: 37141.163 | H178: 238.07225 | L178: 567.03627 | M178: 74.95824 | N178: 398.42862 | O178: 60.296189 | P178: 135.88683 | T178: 1025.7666 | U178: 5959.4305 | V178: 0.18111471 | AA178: 65.0034 | AB178: 0.94094513 | AC178: 58.786201 | AD178: 14641.433 | AE178: 1944.9977 | AF178: 197644.8
A179: 2015 | B179: Masculino | C179: de 1 a 2 | D179: 1709641.4 | E179: 35209.371 | F179: 7986.4629 | G179: 50356.282 | H179: 1150.7639 | L179: 2318.9119 | M179: 420.99148 | N179: 1450.0762 | O179: 209.48009 | P179: 652.76324 | T179: 4034.4902 | U179: 25602.238 | V179: 0.98415588 | AA179: 324.56736 | AB179: 4.4035161 | AC179: 309.41959 | AD179: 30595.659 | AE179: 3257.0284 | AF179: 376923.27
A180: 2015 | B180: Masculino | C180: de 2 a 3 | D180: 4729635.3 | E180: 149050.85 | F180: 15779.557 | G180: 60666.299 | H180: 5996.6423 | L180: 8399.6202 | M180: 2619.4042 | N180: 4798.7747 | O180: 891.96092 | P180: 1827.5512 | T180: 16687.984 | U180: 109315.12 | V180: 446.31281 | AA180: 1770.1938 | AB180: 93.312702 | AC180: 1401.6678 | AD180: 61906.711 | AE180: 4224.9257 | AF180: 603397.13
A181: 2015 | B181: Masculino | C181: de 3 a 5 | D181: 3431413.5 | E181: 170060.15 | F181: 21977.888 | G181: 68840.775 | H181: 8246.8516 | L181: 7805.9677 | M181: 3600.5684 | N181: 6826.1736 | O181: 1014.8472 | P181: 2455.4556 | T181: 17072.188 | U181: 124379.17 | V181: 4530.4334 | AA181: 6624.4812 | AB181: 824.29257 | AC181: 2914.616 | AD181: 60610.17 | AE181: 4288.043 | AF181: 648424.24
A182: 2015 | B182: Masculino | C182: de 5 a 7 | D182: 1351007.2 | E182: 100891.03 | F182: 13865.499 | G182: 40128.634 | H182: 4285.9059 | L182: 3357.927 | M182: 1950.3949 | N182: 4033.4215 | O182: 728.75137 | P182: 1564.6676 | T182: 10755.307 | U182: 75038.172 | V182: 6867.0177 | AA182: 7802.6805 | AB182: 1126.3351 | AC182: 2070.5536 | AD182: 39385.118 | AE182: 2787.3065 | AF182: 399565.39
A183: 2015 | B183: Masculino | C183: de 7 a 10 | D183: 879023.81 | E183: 90414.708 | F183: 13348.456 | G183: 33535.057 | H183: 4283.761 | L183: 2330.8123 | M183: 1579.0109 | N183: 3801.9869 | O183: 645.84041 | P183: 1540.8282 | T183: 7444.0681 | U183: 69293.258 | V183: 10008.55 | AA183: 10278.866 | AB183: 1307.1958 | AC183: 1588.0094 | AD183: 32821.029 | AE183: 2813.2881 | AF183: 354775.38
A184: 2015 | B184: Masculino | C184: de 10 a 15 | D184: 692049.27 | E184: 99147.775 | F184: 15610.562 | G184: 34417.554 | H184: 5839.9788 | L184: 1838.0823 | M184: 1387.4103 | N184: 4134.782 | O184: 701.26597 | P184: 1657.5534 | T184: 4233.4593 | U184: 79600.72 | V184: 14771.453 | AA184: 14480.712 | AB184: 1516.2954 | AC184: 1237.9522 | AD184: 36143.95 | AE184: 2668.1759 | AF184: 397173.87
A185: 2015 | B185: Masculino | C185: de 15 a 20 | D185: 325596.67 | E185: 64341.008 | F185: 11079.554 | G185: 24087.035 | H185: 4428.7334 | L185: 858.26908 | M185: 682.35035 | N185: 2550.6382 | O185: 539.28227 | P185: 1019.8 | T185: 1271.9567 | U185: 53065.365 | V185: 11240.387 | AA185: 10885.473 | AB185: 998.64012 | AC185: 647.83217 | AD185: 23381.179 | AE185: 2337.4601 | AF185: 292684.98
A186: 2015 | B186: Masculino | C186: de 20 a 30 | D186: 287436.57 | E186: 78225.315 | F186: 15124.863 | G186: 30290.862 | H186: 5623.2252 | L186: 748.26174 | M186: 610.2411 | N186: 2912.8667 | O186: 884.22901 | P186: 1111.4276 | T186: 786.31145 | U186: 65599.97 | V186: 15075.623 | AA186: 14499.337 | AB186: 1276.6633 | AC186: 699.04217 | AD186: 33405.568 | AE186: 2404.0091 | AF186: 378333.27
A187: 2015 | B187: Masculino | C187: de 30 a 40 | D187: 110592.54 | E187: 41734.903 | F187: 8681.1627 | G187: 18924.969 | H187: 2892.3683 | L187: 296.55241 | M187: 248.38505 | N187: 1287.4566 | O187: 602.29887 | P187: 429.78657 | T187: 246.38828 | U187: 35748.352 | V187: 8689.5416 | AA187: 8203.3221 | AB187: 762.03768 | AC187: 272.00144 | AD187: 14353.566 | AE187: 1550.4594 | AF187: 222608.93
A188: 2015 | B188: Masculino | C188: de 40 a 60 | D188: 56688.034 | E188: 28998.784 | F188: 8107.2373 | G188: 17770.791 | H188: 1452.6282 | L188: 157.02253 | M188: 129.66865 | N188: 664.24963 | O188: 746.0734 | P188: 252.25608 | T188: 166.74172 | U188: 25440.593 | V188: 6414.5892 | AA188: 5845.7442 | AB188: 707.94935 | AC188: 146.54782 | AD188: 11469.013 | AE188: 2155.5302 | AF188: 205461.76
... A211: 2015 | B211: Não declarado | C211: Todas | D211: 6718.1315 | E211: 346.92464 | F211: 35.560759 | G211: 144.45669 | H211: 15.773977 | L211: 11.770838 | M211: 5.8088136 | N211: 13.826907 | O211: 2.3797486 | P211: 4.0117921 | T211: 29.5686 | U211: 266.92175 | V211: 28.044305 | AA211: 29.758113 | AB211: 3.4314178 | AC211: 5.1958847 | AD211: 93.640752 | AE211: 23.395054 | AF211: 1022.6141
A212: 2014 | B212: Masculino/Feminino/Não declarado | C212: Até 1/2 | D212: 2233244 | E212: 3879.6575 | F212: 18790.647 | G212: 121713.86 | H212: 2744.7665 | L212: 880.58906 | M212: 256.49993 | N212: 3323.1433 | O212: 235.924 | P212: 1034.9881 | T212: 127.73957 | U212: 916.45449 | V212: 57.260384 | AA212: 341.38101 | AB212: 10.110036 | AC212: 294.2464 | AD212: 52441.663 | AF212: 717209.04
A213: 2014 | B213: Masculino/Feminino/Não declarado | C213: Mais de 1/2 a 1 | D213: 1221175 | E213: 11434.375 | F213: 4704.9426 | G213: 51591.574 | H213: 324.40324 | L213: 338.14018 | M213: 98.535919 | N213: 559.67301 | O213: 112.7703 | P213: 122.30467 | T213: 1406.4173 | U213: 8472.1301 | V213: 11.232647 | AA213: 83.060789 | AB213: 1.6481412 | AC213: 73.476283 | AD213: 17641.542 | AF213: 226573.19
A214: 2014 | B214: Masculino/Feminino/Não declarado | C214: Mais de 1 a 2 | D214: 2741730 | E214: 50851.444 | F214: 9506.7897 | G214: 64707.931 | H214: 1410.1215 | L214: 1799.2752 | M214: 577.45491 | N214: 2032.6429 | O214: 417.27476 | P214: 570.38158 | T214: 6174.6374 | U214: 37869.656 | V214: 19.261303 | AA214: 408.40023 | AB214: 3.0906915 | AC214: 392.22962 | AD214: 42382.248 | AF214: 423886.03
A215: 2014 | B215: Masculino/Feminino/Não declarado | C215: Mais de 2 a 3 | D215: 8424898 | E215: 243019.98 | F215: 22573.617 | G215: 90890.929 | H215: 8087.363 | L215: 8726.425 | M215: 3863.4287 | N215: 7500.9357 | O215: 2359.698 | P215: 1781.1017 | T215: 29677.069 | U215: 181023.96 | V215: 549.30087 | AA215: 2435.1908 | AB215: 123.56794 | AC215: 2009.4579 | AD215: 73376.293 | AF215: 830707.27
A216: 2014 | B216: Masculino/Feminino/Não declarado | C216: Mais de 3 a 5 | D216: 6283792 | E216: 283844.18 | F216: 33094.816 | G216: 95776.335 | H216: 12272.454 | L216: 9177.0493 | M216: 5568.9023 | N216: 11414.619 | O216: 2205.0861 | P216: 2400.1121 | T216: 30936.701 | U216: 209869.26 | V216: 6897.9851 | AA216: 10093.866 | AB216: 1377.3976 | AC216: 4573.2783 | AD216: 104250.8 | AF216: 855269.9
A217: 2014 | B217: Masculino/Feminino/Não declarado | C217: Mais de 5 a 7 | D217: 2557690 | E217: 173701.94 | F217: 21571.076 | G217: 57371.339 | H217: 6651.7543 | L217: 3758.7518 | M217: 3019.6125 | N217: 6946.8207 | O217: 1385.3032 | P217: 1529.7391 | T217: 19940.71 | U217: 130469.25 | V217: 10970.786 | AA217: 12379.905 | AB217: 2037.5223 | AC217: 3446.6413 | AD217: 56505.386 | AF217: 545698.51
A218: 2014 | B218: Masculino/Feminino/Não declarado | C218: Mais de 7 a 10 | D218: 1620631 | E218: 151575.02 | F218: 19690.645 | G218: 46338.46 | H218: 6376.1836 | L218: 2607.595 | M218: 2373.9018 | N218: 6371.3189 | O218: 1144.3871 | P218: 1515.6684 | T218: 14323.234 | U218: 116862.73 | V218: 16040.427 | AA218: 16250.84 | AB218: 2448.3589 | AC218: 2658.7726 | AD218: 47008.952 | AF218: 481540.6
A219: 2014 | B219: Masculino/Feminino/Não declarado | C219: Mais de 10 a 15 | D219: 1199481 | E219: 156183.96 | F219: 21380.026 | G219: 48666.414 | H219: 8467.7396 | L219: 2156.41 | M219: 1967.9644 | N219: 6652.2742 | O219: 1204.7059 | P219: 1614.5907 | T219: 7820.8937 | U219: 126299.38 | V219: 22789.763 | AA219: 21987.311 | AB219: 2740.7196 | AC219: 1938.268 | AD219: 50019.013 | AF219: 543950.31
A220: 2014 | B220: Masculino/Feminino/Não declarado | C220: Mais de 15 a 20 | D220: 532434 | E220: 95900.584 | F220: 14245.257 | G220: 29694.484 | H220: 6233.841 | L220: 1016.6073 | M220: 925.5217 | N220: 3906.8054 | O220: 899.53512 | P220: 1008.8998 | T220: 2246.5901 | U220: 79662.783 | V220: 16581.715 | AA220: 15821.706 | AB220: 1702.8299 | AC220: 942.82087 | AD220: 30975.475 | AF220: 354215.26
A221: 2014 | B221: Masculino/Feminino/Não declarado | C221: Mais de 20 a 30 | D221: 474982 | E221: 118457.05 | F221: 18292.014 | G221: 40858.611 | H221: 8479.1156 | L221: 931.33414 | M221: 846.82608 | N221: 4600.1514 | O221: 1380.3515 | P221: 1153.3366 | T221: 1311.5868 | U221: 99754.35 | V221: 22687.53 | AA221: 21727.047 | AB221: 2032.5125 | AC221: 1072.0293 | AD221: 34796.137 | AF221: 478693.59
A222: 2014 | B222: Masculino/Feminino/Não declarado | C222: Mais de 30 a 40 | D222: 168224 | E222: 57720.617 | F222: 10127.246 | G222: 22349.01 | H222: 3913.3827 | L222: 342.00466 | M222: 314.65528 | N222: 1820.759 | O222: 900.04195 | P222: 420.79543 | T222: 383.03119 | U222: 49625.972 | V222: 11973.207 | AA222: 11176.215 | AB222: 1139.9984 | AC222: 343.00662 | AD222: 18080.402 | AF222: 263835.89
A223: 2014 | B223: Masculino/Feminino/Não declarado | C223: Mais de 40 a 60 | D223: 78617 | E223: 36843.494 | F223: 9248.7073 | G223: 18259.362 | H223: 1813.6349 | L223: 170.19687 | M223: 155.91072 | N223: 865.61355 | O223: 927.64564 | P223: 268.46306 | T223: 232.52799 | U223: 32409.501 | V223: 8121.7406 | AA223: 7300.2688 | AB223: 991.76667 | AC223: 170.2949 | AD223: 12171.425 | AF223: 226231.23
... A294: 2008 | B294: Masculino/Feminino/Não declarado | C294: > 160 Salários Mín. | D294: 7613 | E294: 13287.488 | F294: 9273.0825 | G294: 9949.2547 | H294: 273.10858 | L294: 15.920476 | M294: 14.131051 | N294: 103.10042 | O294: 1216.3967 | P294: 54.948928 | T294: 18.712182 | U294: 11597.98 | V294: 3126.6999 | AA294: 2751.7603 | AB294: 409.16525 | AC294: 64.299135 | AD294: 7644.29 | AF294: 118044.02

Sheet Q1_Evolucao
A1: Ano-Calendário | B1: Quantidade de Declarantes | C1: Fórmula
A2: 2015 | B2: =SUMIFS(Dados!$D:$D,Dados!$A:$A,A2,Dados!$B:$B,"Masculino")+SUMIFS(Dados!$D:$D,Dados!$A:$A,A2,Dados!$B:$B,"Feminino") -> 27512126 | C2: =SUMIFS(Dados!$D:$D,Dados!$A:$A,A2,Dados!$B:$B,"Masculino")+SUMIFS(Dados!$D:$D,Dados!$A:$A,A2,Dados!$B:$B,"Feminino") -> 27512126
A3: 2016 | B3: =SUMIFS(Dados!$D:$D,Dados!$A:$A,A3,Dados!$B:$B,"Masculino")+SUMIFS(Dados!$D:$D,Dados!$A:$A,A3,Dados!$B:$B,"Feminino") -> 28913626 | C3: =SUMIFS(Dados!$D:$D,Dados!$A:$A,A3,Dados!$B:$B,"Masculino")+SUMIFS(Dados!$D:$D,Dados!$A:$A,A3,Dados!$B:$B,"Feminino") -> 28913626
A4: 2017 | B4: =SUMIFS(Dados!$D:$D,Dados!$A:$A,A4,Dados!$B:$B,"Masculino")+SUMIFS(Dados!$D:$D,Dados!$A:$A,A4,Dados!$B:$B,"Feminino") -> 29600355 | C4: =SUMIFS(Dados!$D:$D,Dados!$A:$A,A4,Dados!$B:$B,"Masculino")+SUMIFS(Dados!$D:$D,Dados!$A:$A,A4,Dados!$B:$B,"Feminino") -> 29600355
A5: 2018 | B5: =SUMIFS(Dados!$D:$D,Dados!$A:$A,A5,Dados!$B:$B,"Masculino")+SUMIFS(Dados!$D:$D,Dados!$A:$A,A5,Dados!$B:$B,"Feminino") -> 30449617 | C5: =SUMIFS(Dados!$D:$D,Dados!$A:$A,A5,Dados!$B:$B,"Masculino")+SUMIFS(Dados!$D:$D,Dados!$A:$A,A5,Dados!$B:$B,"Feminino") -> 30449617
A6: 2019 | B6: =SUMIFS(Dados!$D:$D,Dados!$A:$A,A6,Dados!$B:$B,"Masculino")+SUMIFS(Dados!$D:$D,Dados!$A:$A,A6,Dados!$B:$B,"Feminino") -> 30495796 | C6: =SUMIFS(Dados!$D:$D,Dados!$A:$A,A6,Dados!$B:$B,"Masculino")+SUMIFS(Dados!$D:$D,Dados!$A:$A,A6,Dados!$B:$B,"Feminino") -> 30495796
A7: 2020 | B7: =SUMIFS(Dados!$D:$D,Dados!$A:$A,A7,Dados!$B:$B,"Masculino")+SUMIFS(Dados!$D:$D,Dados!$A:$A,A7,Dados!$B:$B,"Feminino") -> 31632151 | C7: =SUMIFS(Dados!$D:$D,Dados!$A:$A,A7,Dados!$B:$B,"Masculino")+SUMIFS(Dados!$D:$D,Dados!$A:$A,A7,Dados!$B:$B,"Feminino") -> 31632151

Sheet Q2_Genero
A1: Gênero | B1: Quantidade de Declarantes | C1: Fórmula
A2: Feminino | B2: =SUMIFS(Dados!$D:$D,Dados!$A:$A,2020,Dados!$B:$B,A2) -> 13762031 | C2: =SUMIFS(Dados!$D:$D,Dados!$A:$A,2020,Dados!$B:$B,A2) -> 13762031
A3: Masculino | B3: =SUMIFS(Dados!$D:$D,Dados!$A:$A,2020,Dados!$B:$B,A3) -> 17870120 | C3: =SUMIFS(Dados!$D:$D,Dados!$A:$A,2020,Dados!$B:$B,A3) -> 17870120

Sheet Q3_Faixas
A1: Faixa SM Mensal | B1: Quantidade de Declarantes | C1: Fórmula
A2: Até 1/2 | B2: =SUMIFS(Dados!$D:$D,Dados!$A:$A,2020,Dados!$C:$C,A2,Dados!$B:$B,"Masculino")+SUMIFS(Dados!$D:$D,Dados!$A:$A,2020,Dados!$C:$C,A2,Dados!$B:$B,"Feminino") -> 3301933 | C2: =SUMIFS(Dados!$D:$D,Dados!$A:$A,2020,Dados!$C:$C,A2,Dados!$B:$B,"Masculino")+SUMIFS(Dados!$D:$D,Dados!$A:$A,2020,Dados!$C:$C,A2,Dados!$B:$B,"Feminino") -> 3301933
A3: De 1/2 a 1 | B3: =SUMIFS(Dados!$D:$D,Dados!$A:$A,2020,Dados!$C:$C,A3,Dados!$B:$B,"Masculino")+SUMIFS(Dados!$D:$D,Dados!$A:$A,2020,Dados!$C:$C,A3,Dados!$B:$B,"Feminino") -> 2094637 | C3: =SUMIFS(Dados!$D:$D,Dados!$A:$A,2020,Dados!$C:$C,A3,Dados!$B:$B,"Masculino")+SUMIFS(Dados!$D:$D,Dados!$A:$A,2020,Dados!$C:$C,A3,Dados!$B:$B,"Feminino") -> 2094637
A4: De 1 a 2 | B4: =SUMIFS(Dados!$D:$D,Dados!$A:$A,2020,Dados!$C:$C,A4,Dados!$B:$B,"Masculino")+SUMIFS(Dados!$D:$D,Dados!$A:$A,2020,Dados!$C:$C,A4,Dados!$B:$B,"Feminino") -> 7480081 | C4: =SUMIFS(Dados!$D:$D,Dados!$A:$A,2020,Dados!$C:$C,A4,Dados!$B:$B,"Masculino")+SUMIFS(Dados!$D:$D,Dados!$A:$A,2020,Dados!$C:$C,A4,Dados!$B:$B,"Feminino") -> 7480081
A5: De 2 a 3 | B5: =SUMIFS(Dados!$D:$D,Dados!$A:$A,2020,Dados!$C:$C,A5,Dados!$B:$B,"Masculino")+SUMIFS(Dados!$D:$D,Dados!$A:$A,2020,Dados!$C:$C,A5,Dados!$B:$B,"Feminino") -> 6680718 | C5: =SUMIFS(Dados!$D:$D,Dados!$A:$A,2020,Dados!$C:$C,A5,Dados!$B:$B,"Masculino")+SUMIFS(Dados!$D:$D,Dados!$A:$A,2020,Dados!$C:$C,A5,Dados!$B:$B,"Feminino") -> 6680718
A6: De 3 a 5 | B6: =SUMIFS(Dados!$D:$D,Dados!$A:$A,2020,Dados!$C:$C,A6,Dados!$B:$B,"Masculino")+SUMIFS(Dados!$D:$D,Dados!$A:$A,2020,Dados!$C:$C,A6,Dados!$B:$B,"Feminino") -> 5904544 | C6: =SUMIFS(Dados!$D:$D,Dados!$A:$A,2020,Dados!$C:$C,A6,Dados!$B:$B,"Masculino")+SUMIFS(Dados!$D:$D,Dados!$A:$A,2020,Dados!$C:$C,A6,Dados!$B:$B,"Feminino") -> 5904544
A7: Total até 5 salários mínimos | B7: =SUM(B2:B6) -> 25461913 | C7: =SUM(B2:B6) -> 25461913

Sheet Q4_Rendimentos
A1: Gênero | B1: Rendimentos Tributáveis | C1: Fórmula
A2: Feminino | B2: =SUMIFS(Dados!$E:$E,Dados!$A:$A,2020,Dados!$B:$B,A2) -> 826670.32 | C2: =SUMIFS(Dados!$E:$E,Dados!$A:$A,2020,Dados!$B:$B,A2) -> 826670.32
A3: Masculino | B3: =SUMIFS(Dados!$E:$E,Dados!$A:$A,2020,Dados!$B:$B,A3) -> 1148602.3 | C3: =SUMIFS(Dados!$E:$E,Dados!$A:$A,2020,Dados!$B:$B,A3) -> 1148602.3

Sheet Q5_Media
A1: Ano | B1: Feminino | C1: Masculino | D1: Fórmula Feminino | E1: Fórmula Masculino
A2: 2015 | B2: =SUMIFS(Dados!$D:$D,Dados!$A:$A,A2,Dados!$B:$B,"Feminino") -> 11613399 | C2: =SUMIFS(Dados!$D:$D,Dados!$A:$A,A2,Dados!$B:$B,"Masculino") -> 15898727 | D2: =SUMIFS(Dados!$D:$D,Dados!$A:$A,A2,Dados!$B:$B,"Feminino") -> 11613399 | E2: =SUMIFS(Dados!$D:$D,Dados!$A:$A,A2,Dados!$B:$B,"Masculino") -> 15898727
A3: 2016 | B3: =SUMIFS(Dados!$D:$D,Dados!$A:$A,A3,Dados!$B:$B,"Feminino") -> 12274360 | C3: =SUMIFS(Dados!$D:$D,Dados!$A:$A,A3,Dados!$B:$B,"Masculino") -> 16639266 | D3: =SUMIFS(Dados!$D:$D,Dados!$A:$A,A3,Dados!$B:$B,"Feminino") -> 12274360 | E3: =SUMIFS(Dados!$D:$D,Dados!$A:$A,A3,Dados!$B:$B,"Masculino") -> 16639266
A4: 2017 | B4: =SUMIFS(Dados!$D:$D,Dados!$A:$A,A4,Dados!$B:$B,"Feminino") -> 12642906 | C4: =SUMIFS(Dados!$D:$D,Dados!$A:$A,A4,Dados!$B:$B,"Masculino") -> 16957449 | D4: =SUMIFS(Dados!$D:$D,Dados!$A:$A,A4,Dados!$B:$B,"Feminino") -> 12642906 | E4: =SUMIFS(Dados!$D:$D,Dados!$A:$A,A4,Dados!$B:$B,"Masculino") -> 16957449
A5: 2018 | B5: =SUMIFS(Dados!$D:$D,Dados!$A:$A,A5,Dados!$B:$B,"Feminino") -> 13083422 | C5: =SUMIFS(Dados!$D:$D,Dados!$A:$A,A5,Dados!$B:$B,"Masculino") -> 17366195 | D5: =SUMIFS(Dados!$D:$D,Dados!$A:$A,A5,Dados!$B:$B,"Feminino") -> 13083422 | E5: =SUMIFS(Dados!$D:$D,Dados!$A:$A,A5,Dados!$B:$B,"Masculino") -> 17366195
A6: 2019 | B6: =SUMIFS(Dados!$D:$D,Dados!$A:$A,A6,Dados!$B:$B,"Feminino") -> 13217943 | C6: =SUMIFS(Dados!$D:$D,Dados!$A:$A,A6,Dados!$B:$B,"Masculino") -> 17277853 | D6: =SUMIFS(Dados!$D:$D,Dados!$A:$A,A6,Dados!$B:$B,"Feminino") -> 13217943 | E6: =SUMIFS(Dados!$D:$D,Dados!$A:$A,A6,Dados!$B:$B,"Masculino") -> 17277853
A7: 2020 | B7: =SUMIFS(Dados!$D:$D,Dados!$A:$A,A7,Dados!$B:$B,"Feminino") -> 13762031 | C7: =SUMIFS(Dados!$D:$D,Dados!$A:$A,A7,Dados!$B:$B,"Masculino") -> 17870120 | D7: =SUMIFS(Dados!$D:$D,Dados!$A:$A,A7,Dados!$B:$B,"Feminino") -> 13762031 | E7: =SUMIFS(Dados!$D:$D,Dados!$A:$A,A7,Dados!$B:$B,"Masculino") -> 17870120
A9: Média 2015–2020 | B9: =AVERAGE(B2:B7) -> 12765677 | C9: =AVERAGE(C2:C7) -> 17001602 | D9: =AVERAGE(B2:B7) -> 12765677 | E9: =AVERAGE(C2:C7) -> 17001602
